{
  "version": 1,
  "metadata": {
    "name": "PetFlow Mission Demo",
    "description": "Roadshow demo: Prepare my dog for a weekend trip",
    "schema_version": 1,
    "created_at": null,
    "updated_at": null,
    "tags": ["demo", "mission-control"]
  },
  "nodes": [
    {
      "id": "trip_needs",
      "type": "task",
      "title": "Define trip needs",
      "description": "List destination, travel time, stay length, and dog-specific constraints.",
      "status": "done",
      "priority": 5,
      "estimated_minutes": 20,
      "actual_minutes": 20,
      "x": 120,
      "y": 120,
      "parent_id": null,
      "created_at": null,
      "updated_at": null,
      "completed_at": null,
      "tags": ["mission", "planning"],
      "attachments": [],
      "repeat_type": "none",
      "repeat_days": [],
      "repeat_interval": 1,
      "last_completed_at": null,
      "next_due_at": "2026-05-29T09:00:00+00:00",
      "streak": 0,
      "resource_type": "text",
      "resource_path": "",
      "checklist": [],
      "unlock_condition": "",
      "duration_minutes": 0,
      "locked": false,
      "metadata": {}
    },
    {
      "id": "vaccination_record",
      "type": "resource",
      "title": "Check vaccination record",
      "description": "Find rabies and kennel cough records required by boarding providers.",
      "status": "done",
      "priority": 4,
      "estimated_minutes": 15,
      "actual_minutes": 15,
      "x": 380,
      "y": 40,
      "parent_id": null,
      "created_at": null,
      "updated_at": null,
      "completed_at": null,
      "tags": ["health", "resource"],
      "attachments": [],
      "repeat_type": "none",
      "repeat_days": [],
      "repeat_interval": 1,
      "last_completed_at": null,
      "next_due_at": "2026-05-29T11:00:00+00:00",
      "streak": 0,
      "resource_type": "file",
      "resource_path": "Vaccination-record.pdf",
      "checklist": [],
      "unlock_condition": "",
      "duration_minutes": 0,
      "locked": false,
      "metadata": {}
    },
    {
      "id": "pet_hotel",
      "type": "task",
      "title": "Confirm pet hotel booking",
      "description": "Call the pet hotel, confirm arrival time, vaccination requirements, and emergency contact.",
      "status": "doing",
      "priority": 5,
      "estimated_minutes": 30,
      "actual_minutes": 8,
      "x": 380,
      "y": 190,
      "parent_id": null,
      "created_at": null,
      "updated_at": null,
      "completed_at": null,
      "tags": ["booking"],
      "attachments": [],
      "repeat_type": "none",
      "repeat_days": [],
      "repeat_interval": 1,
      "last_completed_at": null,
      "next_due_at": "2026-05-29T15:00:00+00:00",
      "streak": 0,
      "resource_type": "text",
      "resource_path": "",
      "checklist": [],
      "unlock_condition": "",
      "duration_minutes": 0,
      "locked": false,
      "metadata": {}
    },
    {
      "id": "pack_food",
      "type": "task",
      "title": "Pack food and medicine",
      "description": "Prepare measured meals, treats, supplements, and medication labels.",
      "status": "todo",
      "priority": 4,
      "estimated_minutes": 35,
      "actual_minutes": 0,
      "x": 650,
      "y": 95,
      "parent_id": null,
      "created_at": null,
      "updated_at": null,
      "completed_at": null,
      "tags": ["packing"],
      "attachments": [],
      "repeat_type": "none",
      "repeat_days": [],
      "repeat_interval": 1,
      "last_completed_at": null,
      "next_due_at": "2026-05-30T09:00:00+00:00",
      "streak": 0,
      "resource_type": "text",
      "resource_path": "",
      "checklist": [],
      "unlock_condition": "",
      "duration_minutes": 0,
      "locked": false,
      "metadata": {}
    },
    {
      "id": "leash_carrier",
      "type": "task",
      "title": "Prepare leash and carrier",
      "description": "Check carrier size, collar tag, leash, waste bags, and comfort blanket.",
      "status": "todo",
      "priority": 3,
      "estimated_minutes": 25,
      "actual_minutes": 0,
      "x": 650,
      "y": 255,
      "parent_id": null,
      "created_at": null,
      "updated_at": null,
      "completed_at": null,
      "tags": ["packing"],
      "attachments": [],
      "repeat_type": "none",
      "repeat_days": [],
      "repeat_interval": 1,
      "last_completed_at": null,
      "next_due_at": "2026-05-30T13:00:00+00:00",
      "streak": 0,
      "resource_type": "text",
      "resource_path": "",
      "checklist": [],
      "unlock_condition": "",
      "duration_minutes": 0,
      "locked": false,
      "metadata": {}
    },
    {
      "id": "feeding_schedule",
      "type": "routine",
      "title": "Set feeding schedule",
      "description": "Write feeding times, portions, and medication reminders for each day.",
      "status": "blocked",
      "priority": 4,
      "estimated_minutes": 20,
      "actual_minutes": 0,
      "x": 910,
      "y": 90,
      "parent_id": null,
      "created_at": null,
      "updated_at": null,
      "completed_at": null,
      "tags": ["routine"],
      "attachments": [],
      "repeat_type": "daily",
      "repeat_days": [],
      "repeat_interval": 1,
      "last_completed_at": null,
      "next_due_at": "2026-05-30T18:00:00+00:00",
      "streak": 0,
      "resource_type": "text",
      "resource_path": "",
      "checklist": [],
      "unlock_condition": "",
      "duration_minutes": 0,
      "locked": false,
      "metadata": {}
    },
    {
      "id": "care_notes",
      "type": "checkpoint",
      "title": "Share care notes",
      "description": "Send hotel staff feeding schedule, behavior notes, vet contact, and pickup details.",
      "status": "todo",
      "priority": 5,
      "estimated_minutes": 25,
      "actual_minutes": 0,
      "x": 910,
      "y": 250,
      "parent_id": null,
      "created_at": null,
      "updated_at": null,
      "completed_at": null,
      "tags": ["handoff"],
      "attachments": [],
      "repeat_type": "none",
      "repeat_days": [],
      "repeat_interval": 1,
      "last_completed_at": null,
      "next_due_at": "2026-05-31T09:00:00+00:00",
      "streak": 0,
      "resource_type": "text",
      "resource_path": "",
      "checklist": [],
      "unlock_condition": "",
      "duration_minutes": 0,
      "locked": false,
      "metadata": {}
    },
    {
      "id": "reward_break",
      "type": "reward",
      "title": "Take a break",
      "description": "The mission is ready. Take a short break before departure.",
      "status": "todo",
      "priority": 2,
      "estimated_minutes": 15,
      "actual_minutes": 0,
      "x": 1170,
      "y": 175,
      "parent_id": null,
      "created_at": null,
      "updated_at": null,
      "completed_at": null,
      "tags": ["reward"],
      "attachments": [],
      "repeat_type": "none",
      "repeat_days": [],
      "repeat_interval": 1,
      "last_completed_at": null,
      "next_due_at": "2026-05-31T17:00:00+00:00",
      "streak": 0,
      "resource_type": "text",
      "resource_path": "",
      "checklist": [],
      "unlock_condition": "",
      "duration_minutes": 15,
      "locked": false,
      "metadata": {}
    }
  ],
  "edges": [
    {"id": "edge_1", "source": "trip_needs", "target": "vaccination_record", "type": "dependency", "label": "requirements", "weight": 1.0, "metadata": {}},
    {"id": "edge_2", "source": "trip_needs", "target": "pet_hotel", "type": "dependency", "label": "booking", "weight": 1.0, "metadata": {}},
    {"id": "edge_3", "source": "vaccination_record", "target": "pet_hotel", "type": "dependency", "label": "records ready", "weight": 1.0, "metadata": {}},
    {"id": "edge_4", "source": "pet_hotel", "target": "pack_food", "type": "dependency", "label": "confirmed stay", "weight": 1.0, "metadata": {}},
    {"id": "edge_5", "source": "pet_hotel", "target": "leash_carrier", "type": "dependency", "label": "arrival details", "weight": 1.0, "metadata": {}},
    {"id": "edge_6", "source": "pack_food", "target": "feeding_schedule", "type": "dependency", "label": "meal plan", "weight": 1.0, "metadata": {}},
    {"id": "edge_7", "source": "leash_carrier", "target": "care_notes", "type": "dependency", "label": "handoff kit", "weight": 1.0, "metadata": {}},
    {"id": "edge_8", "source": "feeding_schedule", "target": "care_notes", "type": "recommendation", "label": "care handoff", "weight": 1.0, "metadata": {}},
    {"id": "edge_9", "source": "care_notes", "target": "reward_break", "type": "recommendation", "label": "mission ready", "weight": 1.0, "metadata": {}}
  ],
  "pet": {
    "current_node_id": "pet_hotel",
    "state": "move",
    "x": 0.0,
    "y": 0.0,
    "mood": "focused",
    "speech": "Tracking your current mission.",
    "visible": true,
    "last_updated_at": null
  },
  "workspace": {
    "current_node_id": "pet_hotel",
    "selected_node_ids": [],
    "selected_edge_ids": [],
    "zoom": 0.85,
    "pan_x": 0.0,
    "pan_y": 0.0,
    "active_panel": "graph",
    "focus_mode": true,
    "theme": "light"
  },
  "history": []
}
